Metadata-Version: 2.1
Name: pyegsl
Version: 1.3
Summary: Python easy interface to gsl
Home-page: https://github.com/heitor57/pyegsl
Author: Heitor L. Werneck
Author-email: heitorwerneck@hotmail.com
License: MIT
Platform: UNKNOWN
